setup.cfg
setup.py
mytodo/__init__.py
mytodo/mytodo_cli
mytodo/mytodo_gui
mytodo/mytodo_server
mytodo/tools.py
mytodo.egg-info/PKG-INFO
mytodo.egg-info/SOURCES.txt
mytodo.egg-info/dependency_links.txt
mytodo.egg-info/requires.txt
mytodo.egg-info/top_level.txt
mytodo/img/__init__.py
mytodo/img/close.png
mytodo/img/done.png
mytodo/mytodoweb/__init__.py
mytodo/mytodoweb/config.py
mytodo/mytodoweb/database.py
mytodo/mytodoweb/main.py
mytodo/mytodoweb/tools.py
mytodo/mytodoweb/views.py
mytodo/mytodoweb/templates/api.html