Metadata-Version: 1.0
Name: mytodo
Version: 0.2.3.3
Summary: The free/libre todo list manager
Home-page: https://github.com/mohamed-aziz/mytodo
Author: Mohamed Aziz Knani
Author-email: medazizknani@gmail.com
License: GPL3
Platform: UNKNOWN
